register.v
module reg8_mux_dff(
  input wire clk, rstn, en,
  input wire [7:0] d,
  output reg [7:0] q
);
  wire [7:0] d_in;

  genvar i;
  generate
    for (i = 0; i < 8; i = i + 1) begin : gen_mux
      assign d_in[i] = en ? d[i] : q[i];
    end
  endgenerate

  always @(posedge clk or negedge rstn) begin
    if (!rstn)
      q <= 8'b0;
    else
      q <= d_in;
  end
endmodule

test.v
`timescale 1ns/1ps
module tb;
    reg clk, rstn, en;
    reg [7:0] d;
    wire [7:0] q;

    reg8_mux_dff U (.clk(clk), .rstn(rstn), .en(en), .d(d), .q(q));

    initial begin
        $dumpfile("wave.vcd");
        $dumpvars(0, tb);
    end

    initial begin
        clk = 0;
        forever #5 clk = ~clk;
    end

    initial begin
        rstn = 0; en = 0; d = 8'h00;
        #12 rstn = 1;
        #8 en = 1; d = 8'hA5;
        #10 en = 0; d = 8'h00;
        #30 en = 1; d = 8'h3C;
        #20 en = 0; d = 8'hFF;
        #20 $finish;
    end
endmodule

wave.vcd
$date
	Sat Nov 01 13:01:52 2025
$end
$version
	Icarus Verilog
$end
$timescale
	1ps
$end
$scope module tb $end
$var wire 8 ! q [7:0] $end
$var reg 1 " clk $end
$var reg 8 # d [7:0] $end
$var reg 1 $ en $end
$var reg 1 % rstn $end
$scope module U $end
$var wire 1 " clk $end
$var wire 8 & d [7:0] $end
$var wire 1 $ en $end
$var wire 1 % rstn $end
$var wire 8 ' d_in [7:0] $end
$var reg 8 ( q [7:0] $end
$scope begin gen_mux[0] $end
$upscope $end
$scope begin gen_mux[1] $end
$upscope $end
$scope begin gen_mux[2] $end
$upscope $end
$scope begin gen_mux[3] $end
$upscope $end
$scope begin gen_mux[4] $end
$upscope $end
$scope begin gen_mux[5] $end
$upscope $end
$scope begin gen_mux[6] $end
$upscope $end
$scope begin gen_mux[7] $end
$upscope $end
$upscope $end
$upscope $end
$enddefinitions $end
#0
$dumpvars
b0 (
b0 '
b0 &
0%
0$
b0 #
0"
b0 !
$end
#5000
1"
#10000
0"
#12000
1%
#15000
1"
#20000
b10100101 '
0"
b10100101 #
b10100101 &
1$
#25000
b10100101 !
b10100101 (
1"
#30000
0"
b0 #
b0 &
0$
#35000
1"
#40000
0"
#45000
1"
#50000
0"
#55000
1"
#60000
b111100 '
0"
b111100 #
b111100 &
1$
#65000
b111100 !
b111100 (
1"
#70000
0"
#75000
1"
#80000
0"
b11111111 #
b11111111 &
0$
